{
  "$schema": "https://json.schemastore.org/tsconfig",
  "display": "Default",
  "compilerOptions": {
    "incremental": true,
    "declaration": true,
    "allowJs": true,
    "noEmit": true,
    "verbatimModuleSyntax": false,
    "ignoreDeprecations": "5.0",

    "noImplicitAny": true,
    "strictNullChecks": true,
    "strictFunctionTypes": true,
    "strictBindCallApply": true,
    "strictPropertyInitialization": false,
    "noImplicitThis": true,
    "alwaysStrict": true,
    "resolveJsonModule": true,

    "experimentalDecorators": true,
    "emitDecoratorMetadata": false
  }
}
